cyrillecv/__init__.py
cyrillecv/main.py
cyrillecv-1.0.0.dist-info/METADATA
cyrillecv-1.0.0.dist-info/WHEEL
cyrillecv-1.0.0.dist-info/entry_points.txt
cyrillecv-1.0.0.dist-info/top_level.txt
cyrillecv-1.0.0.dist-info/RECORD
