Metadata-Version: 2.4
Name: cyrillecv
Version: 1.0.0
Summary: CV interactif de Cyrille Gbale
Author: Cyrille Gbale
Author-email: crvgbale@gmail.com
Requires-Dist: rich
Dynamic: author
Dynamic: author-email
Dynamic: requires-dist
Dynamic: summary
